setup.py
common_dist_nan/Binomialdistribution.py
common_dist_nan/Gaussiandistribution.py
common_dist_nan/Generaldistribution.py
common_dist_nan/__init__.py
common_dist_nan.egg-info/PKG-INFO
common_dist_nan.egg-info/SOURCES.txt
common_dist_nan.egg-info/dependency_links.txt
common_dist_nan.egg-info/not-zip-safe
common_dist_nan.egg-info/top_level.txt