Metadata-Version: 1.0
Name: common-dist-nan
Version: 0.1
Summary: Common distributions
Home-page: UNKNOWN
Author: Nguyet Anh Nguyen
Author-email: UNKNOWN
License: UNKNOWN
Platform: UNKNOWN
